json_requirements/__init__.py
json_requirements/manager.py
tests/__init__.py
tests/test_json.py
json_requirements-1.0.5.dist-info/LICENSE
json_requirements-1.0.5.dist-info/METADATA
json_requirements-1.0.5.dist-info/WHEEL
json_requirements-1.0.5.dist-info/top_level.txt
json_requirements-1.0.5.dist-info/RECORD
