Metadata-Version: 2.1
Name: json_requirements
Version: 1.0.5
Summary: Uma biblioteca para gerenciar dependências python em formato JSON
Home-page: https://github.com/DanielMendesSensei/JSON_requirements
Author: Daniel Mendes
Author-email: senseidanielmendes@gmail.com
Classifier: Programming Language :: Python :: 3
Classifier: License :: OSI Approved :: MIT License
Classifier: Operating System :: OS Independent
Requires-Python: >=3.6
License-File: LICENSE
